tensorlogic/__init__.py
tensorlogic/backend.py
tensorlogic/namedtensor.py
tensorlogic/nn.py
tensorlogic/program.py
tensorlogic/relations.py
tensorlogic/utils.py
tensorlogic-0.0.2.dist-info/METADATA
tensorlogic-0.0.2.dist-info/WHEEL
tensorlogic-0.0.2.dist-info/licenses/LICENSE
tensorlogic-0.0.2.dist-info/RECORD
