Metadata-Version: 2.4
Name: tensorlogic
Version: 0.0.2
Summary: Tensor Logic: a named-index tensor language that unifies logic and tensor computation.
Author-email: Davit Buniatyan <davit@activeloop.ai>
License-Expression: Apache-2.0
License-File: LICENSE
Classifier: Development Status :: 3 - Alpha
Classifier: Intended Audience :: Developers
Classifier: Intended Audience :: Science/Research
Classifier: License :: OSI Approved :: Apache Software License
Classifier: Programming Language :: Python :: 3
Classifier: Programming Language :: Python :: 3 :: Only
Classifier: Topic :: Scientific/Engineering :: Artificial Intelligence
Requires-Python: >=3.9
Requires-Dist: numpy>=1.21
Provides-Extra: torch
Requires-Dist: torch>=2.0; extra == 'torch'
